atevery/__init__.py
atevery-0.1.2.dist-info/LICENSE
atevery-0.1.2.dist-info/METADATA
atevery-0.1.2.dist-info/WHEEL
atevery-0.1.2.dist-info/RECORD
