Metadata-Version: 2.1
Name: atevery
Version: 0.1.2
Summary: A periodic task scheduler for asyncio processes.
Home-page: https://github.com/jejung/atevery
License: MIT
Author: Jean Jung
Author-email: jean.jung@rocketmail.com
Requires-Python: >=3.8,<4.0
Classifier: Framework :: AsyncIO
Classifier: License :: OSI Approved :: MIT License
Classifier: Programming Language :: Python :: 3
Classifier: Programming Language :: Python :: 3.8
Classifier: Programming Language :: Python :: 3.9
Classifier: Programming Language :: Python :: 3.10
Classifier: Programming Language :: Python :: 3.11
Classifier: Programming Language :: Python :: 3.12
Classifier: Topic :: Software Development :: Libraries
